Workbook

Sheet README_Projet
A1: SalesInsight BI - Base de données entreprise
A3: Objectif | B3: Créer un projet autonome pour préparer le Master 1 IDA MIAGE : SQL, modélisation, BI, Python, Power BI et Machine Learning.
A4: Étape 1 | B4: Comprendre les tables : Clients, Produits, Employes, Commandes, Lignes_Commandes.
A5: Étape 2 | B5: Importer les feuilles dans PostgreSQL/MySQL ou Power BI.
A6: Étape 3 | B6: Créer un modèle relationnel : Commandes.ID_Client -> Clients.ID_Client ; Lignes_Commandes.ID_Commande -> Commandes.ID_Commande ; Lignes_Commandes.ID_Produit -> Produits.ID_Produit.
A7: Étape 4 | B7: Faire des requêtes SQL : chiffre d’affaires par mois, top produits, clients fidèles, CA par canal.
A8: Étape 5 | B8: Créer un tableau de bord Power BI avec KPI, courbes mensuelles, top produits, carte par ville/pays.
A9: Étape 6 | B9: Ajouter un mini modèle ML en Python : prévoir le CA mensuel ou segmenter les clients.
A10: Attention | B10: Toutes les données sont fictives et générées automatiquement pour l’entraînement.

Sheet Clients
A1: ID_Client | B1: Nom | C1: Prénom | D1: Email | E1: Ville | F1: Région | G1: Pays | H1: Segment | I1: Date_Inscription | J1: Canal_Acquisition | K1: Actif
A2: C0001 | B2: Thomas | C2: Linh | D2: linh.thomas1@example.com | E2: Toulouse | F2: Occitanie | G2: France | H2: PME | I2: 45177 | J2: Réseaux sociaux | K2: Oui
A3: C0002 | B3: Tran | C3: Hugo | D3: hugo.tran2@example.com | E3: Genève | F3: Genève | G3: Suisse | H3: PME | I3: 45016 | J3: Salon professionnel | K3: Oui
A4: C0003 | B4: Dubois | C4: Emma | D4: emma.dubois3@example.com | E4: Bordeaux | F4: Nouvelle-Aquitaine | G4: France | H4: Particulier | I4: 45543 | J4: SEO | K4: Oui
A5: C0004 | B5: Nguyen | C5: Tú | D5: tú.nguyen4@example.com | E5: Genève | F5: Genève | G5: Suisse | H5: Particulier | I5: 45152 | J5: Parrainage | K5: Oui
A6: C0005 | B6: Martin | C6: Bao | D6: bao.martin5@example.com | E6: Lyon | F6: Auvergne-Rhône-Alpes | G6: France | H6: Particulier | I6: 45275 | J6: Publicité | K6: Oui
A7: C0006 | B7: Simon | C7: Anh | D7: anh.simon6@example.com | E7: Paris | F7: Île-de-France | G7: France | H7: Particulier | I7: 45026 | J7: Publicité | K7: Oui
A8: C0007 | B8: Leroy | C8: Noah | D8: noah.leroy7@example.com | E8: Toulouse | F8: Occitanie | G8: France | H8: PME | I8: 45476 | J8: SEO | K8: Non
A9: C0008 | B9: Dubois | C9: Sarah | D9: sarah.dubois8@example.com | E9: Nice | F9: Provence-Alpes-Côte d’Azur | G9: France | H9: Particulier | I9: 45570 | J9: Salon professionnel | K9: Non
A10: C0009 | B10: Vincent | C10: Gabriel | D10: gabriel.vincent9@example.com | E10: Bordeaux | F10: Nouvelle-Aquitaine | G10: France | H10: PME | I10: 44973 | J10: Réseaux sociaux | K10: Oui
A11: C0010 | B11: Durand | C11: Léa | D11: léa.durand10@example.com | E11: Paris | F11: Île-de-France | G11: France | H11: Particulier | I11: 45391 | J11: Publicité | K11: Oui
A12: C0011 | B12: Petit | C12: Gabriel | D12: gabriel.petit11@example.com | E12: Bruxelles | F12: Bruxelles | G12: Belgique | H12: Particulier | I12: 45626 | J12: SEO | K12: Oui
A13: C0012 | B13: Roux | C13: Nathan | D13: nathan.roux12@example.com | E13: Genève | F13: Genève | G13: Suisse | H13: Particulier | I13: 45400 | J13: Parrainage | K13: Oui
... A121: C0120 | B121: Robert | C121: Tom | D121: tom.robert120@example.com | E121: Nantes | F121: Pays de la Loire | G121: France | H121: Particulier | I121: 44982 | J121: Salon professionnel | K121: Oui

Sheet Produits
A1: ID_Produit | B1: Nom_Produit | C1: Catégorie | D1: Marque | E1: Prix_Unitaire_HT | F1: Coût_Achat_HT | G1: Marge_Unitaire_HT | H1: Stock | I1: Statut_Produit
A2: P0001 | B2: Laptop Pro 14 | C2: Informatique | D2: GreenOffice | E2: 1103.64 | F2: 698.7 | G2: 404.94 | H2: 26 | I2: Actif
A3: P0002 | B3: Laptop Pro 14 V2 | C3: Informatique | D3: GreenOffice | E3: 970.58 | F3: 575.22 | G3: 395.36 | H3: 87 | I3: Actif
A4: P0003 | B4: Écran 27 pouces | C4: Informatique | D4: GreenOffice | E4: 216.77 | F4: 153.01 | G4: 63.76 | H4: 29 | I4: Actif
A5: P0004 | B5: Écran 27 pouces V2 | C5: Informatique | D5: NovaTech | E5: 251.56 | F5: 125.22 | G5: 126.34 | H5: 38 | I5: Actif
A6: P0005 | B6: Clavier mécanique | C6: Informatique | D6: DataPlus | E6: 84.94 | F6: 46.97 | G6: 37.97 | H6: 30 | I6: Actif
A7: P0006 | B7: Clavier mécanique V2 | C7: Informatique | D7: ProServices | E7: 80.3 | F7: 50.03 | G7: 30.27 | H7: 57 | I7: Actif
A8: P0007 | B8: Souris ergonomique | C8: Informatique | D8: MiageLab | E8: 39.08 | F8: 27.28 | G8: 11.8 | H8: 150 | I8: Fin de série
A9: P0008 | B9: Souris ergonomique V2 | C9: Informatique | D9: ProServices | E9: 37.91 | F9: 23.85 | G9: 14.06 | H9: 25 | I9: Actif
A10: P0009 | B10: Station d'accueil USB-C | C10: Informatique | D10: NovaTech | E10: 120.37 | F10: 63.87 | G10: 56.5 | H10: 40 | I10: Actif
A11: P0010 | B11: Station d'accueil USB-C V2 | C11: Informatique | D11: GreenOffice | E11: 138.13 | F11: 71.49 | G11: 66.64 | H11: 115 | I11: Actif
A12: P0011 | B12: Chaise ergonomique | C12: Bureau | D12: MiageLab | E12: 196.18 | F12: 95.7 | G12: 100.48 | H12: 180 | I12: Actif
A13: P0012 | B13: Chaise ergonomique V2 | C13: Bureau | D13: DataPlus | E13: 225.64 | F13: 112.16 | G13: 113.48 | H13: 67 | I13: Actif
... A51: P0050 | B51: Hub HDMI V2 | C51: Accessoires | D51: ProServices | E51: 42 | F51: 21.63 | G51: 20.37 | H51: 105 | I51: Actif

Sheet Employes
A1: ID_Employe | B1: Nom | C1: Prénom | D1: Rôle | E1: Agence | F1: Date_Embauche | G1: Objectif_CA_Mensuel_HT
A2: E001 | B2: Richard | C2: Bao | D2: Commercial | E2: Paris | F2: 44555 | G2: 35000
A3: E002 | B3: Lefebvre | C3: Long | D3: Responsable compte | E3: Paris | F3: 45216 | G3: 22000
A4: E003 | B4: Nguyen | C4: Zoé | D4: Conseiller client | E4: Lyon | F4: 45138 | G4: 18000
A5: E004 | B5: Dang | C5: Trang | D5: Responsable compte | E5: Bordeaux | F5: 44786 | G5: 18000
A6: E005 | B6: Laurent | C6: Zoé | D6: Business Developer | E6: Lyon | F6: 45505 | G6: 25000
A7: E006 | B7: Moreau | C7: Zoé | D7: Business Developer | E7: Paris | F7: 44984 | G7: 18000
A8: E007 | B8: Lefebvre | C8: Louis | D8: Conseiller client | E8: Lyon | F8: 45374 | G8: 25000
A9: E008 | B9: Tran | C9: Emma | D9: Commercial | E9: Bordeaux | F9: 44759 | G9: 35000
A10: E009 | B10: Tran | C10: Long | D10: Business Developer | E10: Toulouse | F10: 45438 | G10: 25000
A11: E010 | B11: Dang | C11: Anh | D11: Conseiller client | E11: Paris | F11: 45440 | G11: 22000

Sheet Feuille13
A3: Canal_Vente | B3: Somme de Total_HT
A4: Magasin | B4: 97589.59
A5: Marketplace | B5: 83680.31
A6: Téléphone | B6: 99309.17
A7: Web | B7: 91016.46
A8: Total général | B8: 371595.53
A23: Mois | B23: Somme de Total_HT
A24: 09-2025 | B24: 27449.06
A25: 05-2025 | B25: 22431.28 | E25: Mois | F25: Somme de Somme de Total_HT
A26: 01-2025 | B26: 21157.72 | E26: 09-2025 | F26: 27449.06
A27: 06-2024 | B27: 19776.33 | E27: 05-2025 | F27: 22431.28
A28: 10-2025 | B28: 19723.36 | E28: 01-2025 | F28: 21157.72
A29: 02-2024 | B29: 19635.38 | E29: 06-2024 | F29: 19776.33
A30: 11-2024 | B30: 19557.24 | E30: 10-2025 | F30: 19723.36
A31: 12-2024 | B31: 18742.62 | E31: 02-2024 | F31: 19635.38
A32: 04-2025 | B32: 17147.6 | E32: 11-2024 | F32: 19557.24
A33: 03-2025 | B33: 16764.52 | E33: 12-2024 | F33: 18742.62
A34: 05-2024 | B34: 16102.83 | E34: 04-2025 | F34: 17147.6
A35: 07-2025 | B35: 15420.11 | E35: 03-2025 | F35: 16764.52
A36: 01-2024 | B36: 15307.28 | E36: 05-2024 | F36: 16102.83
A37: 08-2025 | B37: 15108.52 | E37: 07-2025 | F37: 15420.11
... A48: Total général | B48: 371595.53 | E48: 02-2025 | F48: 7372.46
E49: 04-2024 | F49: 6131.2
E50: Total général | F50: 371595.53

Sheet Commandes
A1: ID_Commande | B1: Date_Commande | C1: ID_Client | D1: ID_Employe | E1: Canal_Vente | F1: Statut_Commande | G1: Mode_Paiement | H1: Frais_Livraison_HT | I1: Total_HT | J1: Total_TTC | K1: Mois
A2: CMD00001 | B2: 45943 | C2: C0025 | D2: E010 | E2: Téléphone | F2: Livrée | G2: Virement | H2: 0 | I2: 748.02 | J2: 897.62 | K2: =TEXT(B2,"mm-yyyy") -> 10-2025
A3: CMD00002 | B3: 45497 | C3: C0017 | D3: E009 | E3: Téléphone | F3: Livrée | G3: PayPal | H3: 4.9 | I3: 2103.62 | J3: 2524.34 | K3: =TEXT(B3,"mm-yyyy") -> 07-2024
A4: CMD00003 | B4: 45638 | C4: C0103 | D4: E002 | E4: Marketplace | F4: Annulée | G4: Virement | H4: 4.9 | I4: 1648.02 | J4: 1977.62 | K4: =TEXT(B4,"mm-yyyy") -> 12-2024
A5: CMD00004 | B5: 45980 | C5: C0034 | D5: E010 | E5: Marketplace | F5: Livrée | G5: PayPal | H5: 0 | I5: 559.21 | J5: 671.05 | K5: =TEXT(B5,"mm-yyyy") -> 11-2025
A6: CMD00005 | B6: 46009 | C6: C0039 | D6: E007 | E6: Web | F6: Livrée | G6: Carte bancaire | H6: 7.9 | I6: 821.79 | J6: 986.15 | K6: =TEXT(B6,"mm-yyyy") -> 12-2025
A7: CMD00006 | B7: 45962 | C7: C0013 | D7: E008 | E7: Marketplace | F7: En cours | G7: PayPal | H7: 0 | I7: 528.92 | J7: 634.7 | K7: =TEXT(B7,"mm-yyyy") -> 11-2025
A8: CMD00007 | B8: 45659 | C8: C0008 | D8: E007 | E8: Téléphone | F8: Livrée | G8: Carte bancaire | H8: 12.5 | I8: 602.95 | J8: 723.54 | K8: =TEXT(B8,"mm-yyyy") -> 01-2025
A9: CMD00008 | B9: 45313 | C9: C0007 | D9: E006 | E9: Magasin | F9: Retournée | G9: Virement | H9: 0 | I9: 862.57 | J9: 1035.08 | K9: =TEXT(B9,"mm-yyyy") -> 01-2024
A10: CMD00009 | B10: 45425 | C10: C0070 | D10: E005 | E10: Magasin | F10: Livrée | G10: Carte bancaire | H10: 4.9 | I10: 65.08 | J10: 78.1 | K10: =TEXT(B10,"mm-yyyy") -> 05-2024
A11: CMD00010 | B11: 45470 | C11: C0034 | D11: E001 | E11: Magasin | F11: Livrée | G11: Carte bancaire | H11: 0 | I11: 115.96 | J11: 139.15 | K11: =TEXT(B11,"mm-yyyy") -> 06-2024
A12: CMD00011 | B12: 45921 | C12: C0006 | D12: E009 | E12: Téléphone | F12: Livrée | G12: Carte bancaire | H12: 0 | I12: 1636.29 | J12: 1963.55 | K12: =TEXT(B12,"mm-yyyy") -> 09-2025
A13: CMD00012 | B13: 45853 | C13: C0092 | D13: E006 | E13: Marketplace | F13: Retournée | G13: PayPal | H13: 12.5 | I13: 169.23 | J13: 203.08 | K13: =TEXT(B13,"mm-yyyy") -> 07-2025
... A421: CMD00420 | B421: 45468 | C421: C0091 | D421: E005 | E421: Web | F421: Livrée | G421: Carte bancaire | H421: 4.9 | I421: 49.06 | J421: 58.87 | K421: =TEXT(B421,"mm-yyyy") -> 06-2024

Sheet Lignes_Commandes
A1: ID_Ligne | B1: ID_Commande | C1: ID_Produit | D1: Quantité | E1: Prix_Unitaire_HT | F1: Remise_% | G1: CA_HT | H1: TVA | I1: CA_TTC
A2: L000001 | B2: CMD00001 | C2: P0042 | D2: 1 | E2: 70.8 | F2: 0.05 | G2: 67.26 | H2: 13.45 | I2: 80.71
A3: L000002 | B3: CMD00001 | C3: P0003 | D3: 2 | E3: 216.77 | F3: 0.15 | G3: 368.51 | H3: 73.7 | I3: 442.21
A4: L000003 | B4: CMD00001 | C4: P0009 | D4: 1 | E4: 120.37 | F4: 0 | G4: 120.37 | H4: 24.07 | I4: 144.44
A5: L000004 | B5: CMD00001 | C5: P0021 | D5: 3 | E5: 63.96 | F5: 0 | G5: 191.88 | H5: 38.38 | I5: 230.26
A6: L000005 | B6: CMD00002 | C6: P0031 | D6: 8 | E6: 262.34 | F6: 0 | G6: 2098.72 | H6: 419.74 | I6: 2518.46
A7: L000006 | B7: CMD00003 | C7: P0047 | D7: 2 | E7: 30.71 | F7: 0.05 | G7: 58.35 | H7: 11.67 | I7: 70.02
A8: L000007 | B8: CMD00003 | C8: P0036 | D8: 1 | E8: 454.43 | F8: 0.05 | G8: 431.71 | H8: 86.34 | I8: 518.05
A9: L000008 | B9: CMD00003 | C9: P0001 | D9: 1 | E9: 1103.64 | F9: 0 | G9: 1103.64 | H9: 220.73 | I9: 1324.37
A10: L000009 | B10: CMD00003 | C10: P0030 | D10: 1 | E10: 58.14 | F10: 0.15 | G10: 49.42 | H10: 9.88 | I10: 59.3
A11: L000010 | B11: CMD00004 | C11: P0031 | D11: 1 | E11: 262.34 | F11: 0.1 | G11: 236.11 | H11: 47.22 | I11: 283.33
A12: L000011 | B12: CMD00004 | C12: P0021 | D12: 4 | E12: 63.96 | F12: 0 | G12: 255.84 | H12: 51.17 | I12: 307.01
A13: L000012 | B13: CMD00004 | C13: P0042 | D13: 1 | E13: 70.8 | F13: 0.05 | G13: 67.26 | H13: 13.45 | I13: 80.71
... A966: L000965 | B966: CMD00420 | C966: P0045 | D966: 1 | E966: 44.16 | F966: 0 | G966: 44.16 | H966: 8.83 | I966: 52.99

Sheet Dictionnaire
A1: Table | B1: Champ | C1: Description | D1: Exemple
A2: Clients | B2: ID_Client | C2: Identifiant unique du client | D2: C0001
A3: Clients | B3: Segment | C3: Type de client : Particulier, PME, Grand Compte | D3: PME
A4: Produits | B4: Prix_Unitaire_HT | C4: Prix de vente hors taxe | D4: 89.00
A5: Produits | B5: Coût_Achat_HT | C5: Coût estimé pour calculer la marge | D5: 42.00
A6: Employes | B6: Objectif_CA_Mensuel_HT | C6: Objectif commercial mensuel | D6: 25000
A7: Commandes | B7: Statut_Commande | C7: État de la commande | D7: Livrée
A8: Commandes | B8: Total_HT | C8: Total hors taxe de la commande, frais compris | D8: 532.40
A9: Lignes_Commandes | B9: Quantité | C9: Nombre d’unités vendues | D9: 3
A10: Lignes_Commandes | B10: Remise_% | C10: Remise appliquée à la ligne | D10: 10%
A11: Lignes_Commandes | B11: CA_HT | C11: Chiffre d’affaires hors taxe de la ligne | D11: 240.00
A12: Relations | B12: Commandes.ID_Client | C12: Clé étrangère vers Clients.ID_Client | D12: C0035
... A15: Relations | B15: Lignes_Commandes.ID_Produit | C15: Clé étrangère vers Produits.ID_Produit | D15: P0012

Sheet Dashboard_Base
A1: Dashboard de contrôle - SalesInsight BI
A3: KPI | B3: Formule / Valeur
A4: Nombre de clients | B4: =COUNTA(Clients!A2:A121) -> 120
A5: Nombre de produits | B5: =COUNTA(Produits!A2:A51) -> 50
A6: Nombre de commandes | B6: =COUNTA(Commandes!A2:A421) -> 420
A7: CA livré HT | B7: =SUMIFS(Commandes!I:I,Commandes!F:F,"Livrée") -> 330410.81
A8: Panier moyen livré HT | B8: =IFERROR(B7/COUNTIFS(Commandes!F:F,"Livrée"),0) -> 862.69141
A10: Analyse mensuelle
A11: Mois | B11: CA livré HT
A12: 45292 | B12: =SUMIFS(Commandes!I:I,Commandes!F:F,"Livrée",Commandes!B:B,">="&A12,Commandes!B:B,"<"&EDATE(A12,1)) -> 14186.26
A13: 45323 | B13: =SUMIFS(Commandes!I:I,Commandes!F:F,"Livrée",Commandes!B:B,">="&A13,Commandes!B:B,"<"&EDATE(A13,1)) -> 19635.38
A14: 45352 | B14: =SUMIFS(Commandes!I:I,Commandes!F:F,"Livrée",Commandes!B:B,">="&A14,Commandes!B:B,"<"&EDATE(A14,1)) -> 11714.22
A15: 45383 | B15: =SUMIFS(Commandes!I:I,Commandes!F:F,"Livrée",Commandes!B:B,">="&A15,Commandes!B:B,"<"&EDATE(A15,1)) -> 4913.94
A16: 45413 | B16: =SUMIFS(Commandes!I:I,Commandes!F:F,"Livrée",Commandes!B:B,">="&A16,Commandes!B:B,"<"&EDATE(A16,1)) -> 16102.83
A17: 45444 | B17: =SUMIFS(Commandes!I:I,Commandes!F:F,"Livrée",Commandes!B:B,">="&A17,Commandes!B:B,"<"&EDATE(A17,1)) -> 15460.7
A18: 45474 | B18: =SUMIFS(Commandes!I:I,Commandes!F:F,"Livrée",Commandes!B:B,">="&A18,Commandes!B:B,"<"&EDATE(A18,1)) -> 13255.92
A19: 45505 | B19: =SUMIFS(Commandes!I:I,Commandes!F:F,"Livrée",Commandes!B:B,">="&A19,Commandes!B:B,"<"&EDATE(A19,1)) -> 8491.38
A20: 45536 | B20: =SUMIFS(Commandes!I:I,Commandes!F:F,"Livrée",Commandes!B:B,">="&A20,Commandes!B:B,"<"&EDATE(A20,1)) -> 8175.66
A21: 45566 | B21: =SUMIFS(Commandes!I:I,Commandes!F:F,"Livrée",Commandes!B:B,">="&A21,Commandes!B:B,"<"&EDATE(A21,1)) -> 10064.77
A22: 45597 | B22: =SUMIFS(Commandes!I:I,Commandes!F:F,"Livrée",Commandes!B:B,">="&A22,Commandes!B:B,"<"&EDATE(A22,1)) -> 16852.3
A23: 45627 | B23: =SUMIFS(Commandes!I:I,Commandes!F:F,"Livrée",Commandes!B:B,">="&A23,Commandes!B:B,"<"&EDATE(A23,1)) -> 15951.51
... A35: 45992 | B35: =SUMIFS(Commandes!I:I,Commandes!F:F,"Livrée",Commandes!B:B,">="&A35,Commandes!B:B,"<"&EDATE(A35,1)) -> 10774.14

Sheet KPI_Analyse
A1: Chiffre d’affaires total | B1: =SUM(Lignes_Commandes!I:I) -> 442791.38
A2: Nombre de commandes | B2: =COUNTA(Commandes!A2:A421) -> 420
A3: Nombre de clients | B3: =COUNTA(Clients!A2:A121) -> 120
A4: Panier moyen | B4: =B1/B2 -> 1054.2652
A5: Nombre de produits vendus | B5: =SUM(Lignes_Commandes!D:D) -> 2097

Sheet Analyse_Ventes
A1: ID_Ligne | B1: ID_Commande | C1: ID_Produit | D1: Quantité | E1: Prix_Unitaire_HT | F1: Remise_% | G1: CA_HT | H1: TVA | I1: CA_TTC | J1: Date_Commande
A2: L000001 | B2: CMD00001 | C2: P0042 | D2: 1 | E2: 70.8 | F2: 0.05 | G2: 67.26 | H2: 13.45 | I2: 80.71 | J2: {=INDEX(Commandes!$B$2:$B$421,MATCH(B2,Commandes!$A$2:$A$421,0))} -> 45943
A3: L000002 | B3: CMD00001 | C3: P0003 | D3: 2 | E3: 216.77 | F3: 0.15 | G3: 368.51 | H3: 73.7 | I3: 442.21 | J3: {=INDEX(Commandes!$B$2:$B$421,MATCH(B3,Commandes!$A$2:$A$421,0))} -> 45943
A4: L000003 | B4: CMD00001 | C4: P0009 | D4: 1 | E4: 120.37 | F4: 0 | G4: 120.37 | H4: 24.07 | I4: 144.44 | J4: {=INDEX(Commandes!$B$2:$B$421,MATCH(B4,Commandes!$A$2:$A$421,0))} -> 45943
A5: L000004 | B5: CMD00001 | C5: P0021 | D5: 3 | E5: 63.96 | F5: 0 | G5: 191.88 | H5: 38.38 | I5: 230.26 | J5: {=INDEX(Commandes!$B$2:$B$421,MATCH(B5,Commandes!$A$2:$A$421,0))} -> 45943
A6: L000005 | B6: CMD00002 | C6: P0031 | D6: 8 | E6: 262.34 | F6: 0 | G6: 2098.72 | H6: 419.74 | I6: 2518.46 | J6: {=INDEX(Commandes!$B$2:$B$421,MATCH(B6,Commandes!$A$2:$A$421,0))} -> 45497
A7: L000006 | B7: CMD00003 | C7: P0047 | D7: 2 | E7: 30.71 | F7: 0.05 | G7: 58.35 | H7: 11.67 | I7: 70.02 | J7: {=INDEX(Commandes!$B$2:$B$421,MATCH(B7,Commandes!$A$2:$A$421,0))} -> 45638
A8: L000007 | B8: CMD00003 | C8: P0036 | D8: 1 | E8: 454.43 | F8: 0.05 | G8: 431.71 | H8: 86.34 | I8: 518.05 | J8: {=INDEX(Commandes!$B$2:$B$421,MATCH(B8,Commandes!$A$2:$A$421,0))} -> 45638
A9: L000008 | B9: CMD00003 | C9: P0001 | D9: 1 | E9: 1103.64 | F9: 0 | G9: 1103.64 | H9: 220.73 | I9: 1324.37 | J9: {=INDEX(Commandes!$B$2:$B$421,MATCH(B9,Commandes!$A$2:$A$421,0))} -> 45638
A10: L000009 | B10: CMD00003 | C10: P0030 | D10: 1 | E10: 58.14 | F10: 0.15 | G10: 49.42 | H10: 9.88 | I10: 59.3 | J10: {=INDEX(Commandes!$B$2:$B$421,MATCH(B10,Commandes!$A$2:$A$421,0))} -> 45638
A11: L000010 | B11: CMD00004 | C11: P0031 | D11: 1 | E11: 262.34 | F11: 0.1 | G11: 236.11 | H11: 47.22 | I11: 283.33 | J11: {=INDEX(Commandes!$B$2:$B$421,MATCH(B11,Commandes!$A$2:$A$421,0))} -> 45980
A12: L000011 | B12: CMD00004 | C12: P0021 | D12: 4 | E12: 63.96 | F12: 0 | G12: 255.84 | H12: 51.17 | I12: 307.01 | J12: {=INDEX(Commandes!$B$2:$B$421,MATCH(B12,Commandes!$A$2:$A$421,0))} -> 45980
A13: L000012 | B13: CMD00004 | C13: P0042 | D13: 1 | E13: 70.8 | F13: 0.05 | G13: 67.26 | H13: 13.45 | I13: 80.71 | J13: {=INDEX(Commandes!$B$2:$B$421,MATCH(B13,Commandes!$A$2:$A$421,0))} -> 45980
... A966: L000965 | B966: CMD00420 | C966: P0045 | D966: 1 | E966: 44.16 | F966: 0 | G966: 44.16 | H966: 8.83 | I966: 52.99 | J966: {=INDEX(Commandes!$B$2:$B$421,MATCH(B966,Commandes!$A$2:$A$421,0))} -> 45468

Sheet Dashboard_Final
A1: SalesInsight BI — Dashboard des ventes Analyse des ventes 2024–2025
B2: Chiffre d’affaires HT total 743 191,06 € | H2: Nombre de commandes 420 | M2: Panier moyen HT 1 769,50 € | R2: Meilleur mois 09-2025 | W2: Meilleur canal Téléphone
H37: CONCLUSION Le mois le plus performant est septembre 2025, avec un chiffre d’affaires HT de 27 449,06 €. Le canal Téléphone est le plus rentable avec 99 309,17 €, suivi par Magasin avec 97 589,59 €. Le canal Marketplace est le moins performant avec 83 680,31 €, ce qui peut représenter un axe d’amélioration commerciale.
